pyuikit/__init__.py
pyuikit/app.py
pyuikit/div.py
pyuikit/logo.ico
pyuikit/components/__init__.py
pyuikit/components/button.py
pyuikit/components/checkbox.py
pyuikit/components/dropdown.py
pyuikit/components/filedialog.py
pyuikit/components/input.py
pyuikit/components/progressbar.py
pyuikit/components/radiobutton.py
pyuikit/components/slider.py
pyuikit/components/switch.py
pyuikit/components/text.py
pyuikit/components/toast.py
pyuikit-1.1.1.dist-info/licenses/LICENSE
pyuikit-1.1.1.dist-info/METADATA
pyuikit-1.1.1.dist-info/WHEEL
pyuikit-1.1.1.dist-info/top_level.txt
pyuikit-1.1.1.dist-info/RECORD
