Metadata-Version: 2.4
Name: pyuikit
Version: 1.1.1
Summary: A modern UI library for Python aiming simplicity.
Home-page: https://github.com/Huzaifa-atiq/pyuikit
Author: Muhammad Huzaifa Atiq
License: MIT
License-File: LICENSE
Requires-Dist: customtkinter
Dynamic: author
Dynamic: description
Dynamic: description-content-type
Dynamic: home-page
Dynamic: license
Dynamic: license-file
Dynamic: requires-dist
Dynamic: summary
